pytest_reporter_html_dots/__init__.py
pytest_reporter_html_dots/plugin.py
pytest_reporter_html_dots/templates/html-dots/base.html
pytest_reporter_html_dots/templates/html-dots/index.html
pytest_reporter_html_dots/templates/html-dots/module.html
pytest_reporter_html_dots/templates/html-dots/normalize.css
pytest_reporter_html_dots/templates/html-dots/style.css
pytest_reporter_html_dots/templates/html-dots/test.html
pytest_reporter_html_dots/templates/html-dots/icons/arrow.svg
pytest_reporter_html_dots/templates/html-dots/icons/nok.svg
pytest_reporter_html_dots/templates/html-dots/icons/ok.svg
pytest_reporter_html_dots/templates/html-dots/icons/skip.svg
pytest_reporter_html_dots-0.11.0.dist-info/entry_points.txt
pytest_reporter_html_dots-0.11.0.dist-info/licenses/LICENSE
pytest_reporter_html_dots-0.11.0.dist-info/WHEEL
pytest_reporter_html_dots-0.11.0.dist-info/METADATA
pytest_reporter_html_dots-0.11.0.dist-info/RECORD
