Metadata-Version: 2.4
Name: pytest-reporter-html-dots
Version: 0.11.0
Summary: A basic HTML report for pytest using Jinja2 template engine.
Author-email: erzo <erzo@posteo.de>
Requires-Python: >=3.5
Classifier: Framework :: Pytest
Classifier: Intended Audience :: Developers
Classifier: Topic :: Software Development :: Testing
Classifier: Topic :: Text Processing :: Markup :: HTML
Classifier: Programming Language :: Python
Classifier: Operating System :: OS Independent
Classifier: License :: OSI Approved :: MIT License
License-File: LICENSE
Requires-Dist: pytest-reporter>=0.4.0
Requires-Dist: Jinja2
Requires-Dist: ansi2html>=1.3.0
Requires-Dist: htmlmin2
Requires-Dist: docutils
Project-URL: Home, https://gitlab.com/erzo/pytest-reporter-html-dots
